{"locale":"en","urlPathnameLocalized":"/svelte-kit/","pageId":"/pages/(docs)/(generated)/svelte-kit","routeParams":{},"data":{"config":{"tableOfContents":true},"docSlug":"svelte-kit","headings":[{"depth":2,"id":"1-install-telefunc","title":"1. Install Telefunc"},{"depth":2,"id":"2-plugin-to-vite","title":"2. Plugin to Vite"},{"depth":2,"id":"3-add-telefunc-middleware","title":"3. Add Telefunc middleware"},{"depth":2,"id":"4-initial-data","title":"4. Initial data"},{"depth":2,"id":"next","title":"Next"},{"depth":2,"id":"examples","title":"Examples"}],"resolvedLocale":"en"}}